[
  {
    "id": "40000000-0000-4000-8000-000000000001",
    "title": "数据结构课程助教",
    "moduleOrganiserId": "20000000-0000-4000-8000-000000000001",
    "description": "负责习题课答疑、作业批改与上机辅导，每周约 6 课时。要求熟悉树、图与排序算法。",
    "requiredSkills": ["Java 或 C++", "数据结构", "沟通表达"],
    "type": "course_ta",
    "status": "open",
    "createdAt": 1772400000000
  },
  {
    "id": "40000000-0000-4000-8000-000000000002",
    "title": "软件工程课程助教",
    "moduleOrganiserId": "20000000-0000-4000-8000-000000000002",
    "description": "协助项目评审、文档规范检查与敏捷站会记录。",
    "requiredSkills": ["软件工程", "Java", "团队协作"],
    "type": "course_ta",
    "status": "open",
    "createdAt": 1772486400000
  },
  {
    "id": "40000000-0000-4000-8000-000000000003",
    "title": "2026 春季期末考试监考",
    "moduleOrganiserId": "20000000-0000-4000-8000-000000000001",
    "description": "机房与教室混合排考，需提前 30 分钟到场签到。",
    "requiredSkills": ["监考", "责任心"],
    "type": "invigilation",
    "status": "open",
    "createdAt": 1772572800000
  },
  {
    "id": "40000000-0000-4000-8000-000000000004",
    "title": "Python 程序设计助教",
    "moduleOrganiserId": "20000000-0000-4000-8000-000000000002",
    "description": "上机课答疑与作业批改，已招满。",
    "requiredSkills": ["Python", "基础编程"],
    "type": "course_ta",
    "status": "closed",
    "createdAt": 1772659200000
  },
  {
    "id": "40000000-0000-4000-8000-000000000005",
    "title": "网络安全实验课助教",
    "moduleOrganiserId": "20000000-0000-4000-8000-000000000003",
    "description": "实验环境维护、实验报告初评与安全工具演示。",
    "requiredSkills": ["网络安全", "Linux", "Wireshark"],
    "type": "course_ta",
    "status": "open",
    "createdAt": 1772745600000
  },
  {
    "id": "40000000-0000-4000-8000-000000000006",
    "title": "学术讲座现场志愿者",
    "moduleOrganiserId": "20000000-0000-4000-8000-000000000003",
    "description": "负责签到、引导与物资搬运，周末半天。",
    "requiredSkills": ["活动组织", "沟通"],
    "type": "activity",
    "status": "open",
    "createdAt": 1772832000000
  }
]
